{
  "formatVersion": 0,
  "pmdVersion": "6.41.0",
  "timestamp": "2022-01-08T14:40:50.201+08:00",
  "files": [
    {
      "filename": "C:\\Users\\wanna\\projects\\SAMutator\\seeds\\PMD_Seeds\\errorprone_AvoidFieldNameMatchingMethodName\\AvoidFieldNameMatchingMethodName1.java",
      "violations": [
        {
          "beginline": 4,
          "begincolumn": 9,
          "endline": 4,
          "endcolumn": 16,
          "description": "Field foo has the same name as a method",
          "rule": "AvoidFieldNameMatchingMethodName",
          "ruleset": "Error Prone",
          "priority": 3,
          "externalInfoUrl": "https://pmd.github.io/pmd-6.41.0/pmd_rules_java_errorprone.html#avoidfieldnamematchingmethodname"
        }
      ]
    }
  ],
  "suppressedViolations": [],
  "processingErrors": [],
  "configurationErrors": []
}