{
  "formatVersion": 0,
  "pmdVersion": "6.41.0",
  "timestamp": "2022-01-08T14:35:28.643+08:00",
  "files": [
    {
      "filename": "C:\\Users\\wanna\\projects\\SAMutator\\seeds\\PMD_Seeds\\documentation_UncommentedEmptyConstructor\\UncommentedEmptyConstructor0.java",
      "violations": [
        {
          "beginline": 3,
          "begincolumn": 5,
          "endline": 4,
          "endcolumn": 5,
          "description": "Document empty constructor",
          "rule": "UncommentedEmptyConstructor",
          "ruleset": "Documentation",
          "priority": 3,
          "externalInfoUrl": "https://pmd.github.io/pmd-6.41.0/pmd_rules_java_documentation.html#uncommentedemptyconstructor"
        }
      ]
    }
  ],
  "suppressedViolations": [],
  "processingErrors": [],
  "configurationErrors": []
}