{
  "formatVersion": 0,
  "pmdVersion": "6.41.0",
  "timestamp": "2022-01-08T14:42:30.355+08:00",
  "files": [
    {
      "filename": "C:\\Users\\wanna\\projects\\SAMutator\\seeds\\PMD_Seeds\\performance_UseStringBufferForStringAppends\\UseStringBufferForStringAppends12.java",
      "violations": [
        {
          "beginline": 10,
          "begincolumn": 26,
          "endline": 10,
          "endcolumn": 26,
          "description": "Prefer StringBuilder (non-synchronized) or StringBuffer (synchronized) over +\u003d for concatenating strings",
          "rule": "UseStringBufferForStringAppends",
          "ruleset": "Performance",
          "priority": 3,
          "externalInfoUrl": "https://pmd.github.io/pmd-6.41.0/pmd_rules_java_performance.html#usestringbufferforstringappends"
        },
        {
          "beginline": 14,
          "begincolumn": 26,
          "endline": 14,
          "endcolumn": 26,
          "description": "Prefer StringBuilder (non-synchronized) or StringBuffer (synchronized) over +\u003d for concatenating strings",
          "rule": "UseStringBufferForStringAppends",
          "ruleset": "Performance",
          "priority": 3,
          "externalInfoUrl": "https://pmd.github.io/pmd-6.41.0/pmd_rules_java_performance.html#usestringbufferforstringappends"
        },
        {
          "beginline": 21,
          "begincolumn": 17,
          "endline": 21,
          "endcolumn": 18,
          "description": "Prefer StringBuilder (non-synchronized) or StringBuffer (synchronized) over +\u003d for concatenating strings",
          "rule": "UseStringBufferForStringAppends",
          "ruleset": "Performance",
          "priority": 3,
          "externalInfoUrl": "https://pmd.github.io/pmd-6.41.0/pmd_rules_java_performance.html#usestringbufferforstringappends"
        },
        {
          "beginline": 23,
          "begincolumn": 40,
          "endline": 23,
          "endcolumn": 41,
          "description": "Prefer StringBuilder (non-synchronized) or StringBuffer (synchronized) over +\u003d for concatenating strings",
          "rule": "UseStringBufferForStringAppends",
          "ruleset": "Performance",
          "priority": 3,
          "externalInfoUrl": "https://pmd.github.io/pmd-6.41.0/pmd_rules_java_performance.html#usestringbufferforstringappends"
        },
        {
          "beginline": 30,
          "begincolumn": 26,
          "endline": 30,
          "endcolumn": 27,
          "description": "Prefer StringBuilder (non-synchronized) or StringBuffer (synchronized) over +\u003d for concatenating strings",
          "rule": "UseStringBufferForStringAppends",
          "ruleset": "Performance",
          "priority": 3,
          "externalInfoUrl": "https://pmd.github.io/pmd-6.41.0/pmd_rules_java_performance.html#usestringbufferforstringappends"
        }
      ]
    }
  ],
  "suppressedViolations": [],
  "processingErrors": [],
  "configurationErrors": []
}